APTRS
accounts
customers
project
vulnerability
