Metadata-Version: 2.1
Name: aptrs
Version: 0.0.1
Summary: Automated Penetration Testing Reporting System
Home-page: https://github.com/Anof-cyber/APTRS
Author: AnoF
Author-email: kalalsourav20@gmail.com
Requires-Python: >=3.8<=3.9
License-File: LICENSE
